parcelbright/__init__.py
parcelbright-0.3.3.dist-info/DESCRIPTION.rst
parcelbright-0.3.3.dist-info/WHEEL
parcelbright-0.3.3.dist-info/top_level.txt
parcelbright-0.3.3.dist-info/RECORD
parcelbright-0.3.3.dist-info/metadata.json
parcelbright-0.3.3.dist-info/METADATA
