Metadata-Version: 2.0
Name: parcelbright
Version: 0.3.3
Summary: ParcelBright API wrapper
Home-page: https://github.com/onjin/parcelbright-python
Author: Marek Wywiał
Author-email: onjinx@gmail.com
License: BSD
Keywords: parcelbright
Platform: UNKNOWN
Classifier: Development Status :: 5 - Production/Stable
Classifier: Intended Audience :: Developers
Classifier: License :: OSI Approved :: BSD License
Classifier: Natural Language :: English
Classifier: Programming Language :: Python :: 2
Classifier: Programming Language :: Python :: 2.6
Classifier: Programming Language :: Python :: 2.7
Classifier: Programming Language :: Python :: 3
Classifier: Programming Language :: Python :: 3.3
Classifier: Programming Language :: Python :: 3.4
Requires-Dist: requests
Requires-Dist: schematics
